gsdriver/__init__.py
gsdriver/base/__init__.py
gsdriver/base/abstract.py
gsdriver/base/gcloud.py
gsdriver/base/selenium.py
gsdriver/base/session.py
gsdriver/base/spider.py
gsdriver/base/types.py
gsdriver/utils/__init__.py
gsdriver/utils/alert.py
gsdriver/utils/cast.py
gsdriver/utils/date.py
gsdriver/utils/logs.py
gsdriver/utils/map.py
gsdriver/utils/request.py
gcp_webdriver-0.1.2.dist-info/LICENSE
gcp_webdriver-0.1.2.dist-info/METADATA
gcp_webdriver-0.1.2.dist-info/WHEEL
gcp_webdriver-0.1.2.dist-info/top_level.txt
gcp_webdriver-0.1.2.dist-info/RECORD
