Metadata-Version: 2.2
Name: gcp-webdriver
Version: 0.1.2
Summary: Selenium WebDriver utils with GCP functions
Home-page: https://github.com/minyeamer/gsdriver.git
Author: minyeamer
Author-email: minyeamer@gmail.com
License: minyeamer
Keywords: gcp-webdriver,webdriver,gcp
Requires-Python: >=3.7
License-File: LICENSE
Requires-Dist: tqdm>=4.64.0
Requires-Dist: asyncio>=3.4.3
Requires-Dist: python-dateutil>=2.8.2
Requires-Dist: pandas>=1.4.2
Requires-Dist: openpyxl>=3.1.2
Requires-Dist: bs4>=0.0.1
Requires-Dist: requests>=2.31.1
Requires-Dist: aiohttp>=3.9.1
Requires-Dist: lxml>=4.9.4
Requires-Dist: PyJWT>=2.9.0
Requires-Dist: selenium>=4.8.2
Requires-Dist: selenium-wire>=5.1.0
Requires-Dist: blinker==1.7.0
Requires-Dist: webdriver_manager>=4.0.1
Requires-Dist: pyperclip>=1.8.2
Requires-Dist: gspread>=5.6.2
Requires-Dist: google-cloud-bigquery>=3.4.0
Requires-Dist: holidays>=0.43
Requires-Dist: workalendar>=17.0.0
Dynamic: author
Dynamic: author-email
Dynamic: home-page
Dynamic: keywords
Dynamic: license
Dynamic: requires-dist
Dynamic: requires-python
Dynamic: summary
